almadenkorea/__init__.py
almadenkorea/db.py
almadenkorea-0.0.3.dist-info/METADATA
almadenkorea-0.0.3.dist-info/WHEEL
almadenkorea-0.0.3.dist-info/top_level.txt
almadenkorea-0.0.3.dist-info/RECORD
